whistling_duck/__init__.py
whistling_duck/main.py
whistling_duck-0.2.dist-info/LICENSE
whistling_duck-0.2.dist-info/METADATA
whistling_duck-0.2.dist-info/WHEEL
whistling_duck-0.2.dist-info/top_level.txt
whistling_duck-0.2.dist-info/RECORD
