Metadata-Version: 2.1
Name: whistling-duck
Version: 0.2
Summary: Whistling Duck is a Python library for data quality exploration and validation, designed for small to medium-sized datasets. It is written using DuckDB.
Home-page: https://github.com/thewhistlingducklib/whistlingduck
Author: Subha Saha
Author-email: whistlingducklib@gmail.com
License-File: LICENSE
Requires-Dist: duckdb >=0.10.2
